[{"domain": ".mail.qq.com", "expiry": 1724485119, "httpOnly": false, "name": "webp",
  "path": "/", "sameSite": "Lax", "secure": false, "value": "1"},
  {"domain": ".mail.qq.com", "expiry": 1695541116, "httpOnly": false,
    "name": "CCSHOW", "path": "/", "sameSite": "Lax", "secure": false,
    "value": "000000"}, {"domain": ".mail.qq.com", "expiry": 1695541117,
  "httpOnly": false, "name": "edition", "path": "/", "sameSite": "Lax",
  "secure": false, "value": "mail.qq.com"}, {"domain": ".mail.qq.com",
  "expiry": 1695541117, "httpOnly": false, "name": "qm_logintype",
  "path": "/", "sameSite": "Lax", "secure": false, "value": "qq"},
  {"domain": ".mail.qq.com", "httpOnly": true, "name": "xm_data_ticket",
    "path": "/", "sameSite": "Lax", "secure": true,
    "value": "13102661339458824&CAESIGToWn0ALozNEsAtCL3FTAoryypuutKLneKThuT7y_9p"},
  {"domain": ".mail.qq.com", "httpOnly": false, "name": "xm_ws", "path": "/", "sameSite":
  "Lax", "secure": false, "value": "13102661339458824&bf3a76fd133e4fde22e0436cdc05c086"},
  {"domain": ".mail.qq.com", "httpOnly": false, "name": "qm_muti_sid", "path": "/", "sameSite": "Lax", "secure": false, "value": "13102661339458824&DgYGdFkXl1e-bH4a"}, {"domain": ".mail.qq.com", "httpOnly": false, "name": "sid", "path": "/", "sameSite": "Lax", "secure": false, "value": "314584328&529fc94cd40487ffa8dd895a25a8538c"}, {"domain": ".mail.qq.com", "httpOnly": true, "name": "xm_skey", "path": "/", "sameSite": "Lax", "secure": false, "value": "13102661339458824&467b49e3de005147abd504cd2b7af751"}, {"domain": ".mail.qq.com", "httpOnly": false, "name": "qm_domain", "path": "/", "sameSite": "Lax", "secure": false, "value": "https://mail.qq.com"}, {"domain": ".mail.qq.com", "httpOnly": false, "name": "xm_muti_sid", "path": "/", "sameSite": "Lax", "secure": false, "value": "13102661339458824&zQh2bYwtWXMuwHRSABJjVwAA"}, {"domain": ".qq.com", "expiry": 1727509113, "httpOnly": false, "name": "RK", "path": "/", "sameSite": "Lax", "secure": false, "value": "vIXEA9n8Qu"}, {"domain": ".mail.qq.com", "expiry": 1700725117, "httpOnly": true, "name": "xm_pcache", "path": "/", "sameSite": "Lax", "secure": true, "value": "13102661339458824&V2@fbShuxCnQRagQytp9PqWwgAA@0"}, {"domain": ".mail.qq.com", "httpOnly": false, "name": "ssl_edition", "path": "/", "sameSite": "Lax", "secure": false, "value": "sail.qq.com"}, {"domain": ".mail.qq.com", "httpOnly": false, "name": "username", "path": "/", "sameSite": "Lax", "secure": false, "value": "314584328&314584328"}, {"domain": ".mail.qq.com", "httpOnly": false, "name": "qm_username", "path": "/", "sameSite": "Lax", "secure": false, "value": "314584328"}, {"domain": ".mail.qq.com", "httpOnly": false, "name": "xm_sid", "path": "/", "sameSite": "Lax", "secure": false, "value": "zQh2bYwtWXMuwHRSABJjVwAA"}, {"domain": ".mail.qq.com", "expiry": 1695541117, "httpOnly": false, "name": "qm_device_id", "path": "/", "sameSite": "Lax", "secure": false, "value": "q2pGUCFAGFjHDptIVZdjBsGE6JtL8x4KIRlW53AacotnSubOBFdHvM6QtQao7MBJ"}, {"domain": ".qq.com", "httpOnly": false, "name": "_qpsvr_localtk", "path": "/", "sameSite": "Lax", "secure": false, "value": "0.03773544226672332"}, {"domain": ".qq.com", "expiry": 1727509113, "httpOnly": false, "name": "ptcz", "path": "/", "sameSite": "Lax", "secure": false, "value": "261c7091cc67ed85fb1d7d0fa6fba53dba4385c2c9805edaaeb851b9f6903f35"}, {"domain": ".mail.qq.com", "httpOnly": false, "name": "xm_uin", "path": "/", "sameSite": "Lax", "secure": false, "value": "13102661339458824"}, {"domain": ".mail.qq.com", "expiry": 1724485117, "httpOnly": true, "name": "xm_envid", "path": "/", "sameSite": "Lax", "secure": true, "value": "456_i1X/2MbPn2TXxdjLhsrqxx8mbkn4RunOKdLkvFBmSsGb0dDxbiEeC+nxImEpPENPVIGeV7ESEUcX4RTfMGQqMQ2qIHdGH1F4bnS4UVRLZ/kzmbAAN29vWyvdjGGq98HC30Pdy4Nyvw3CJMO2h02kScY6Nc5jznsjZA=="}, {"domain": ".qq.com", "expiry": 1695541113, "httpOnly": false, "name": "ptui_loginuin", "path": "/", "sameSite": "Lax", "secure": false, "value": "314584328"}, {"domain": ".qq.com", "httpOnly": false, "name": "uin", "path": "/", "sameSite": "Lax", "secure": false, "value": "o314584328"}]